nonebot_plugin_mcnews-0.2.2.dist-info/METADATA
nonebot_plugin_mcnews-0.2.2.dist-info/WHEEL
nonebot_plugin_mcnews-0.2.2.dist-info/entry_points.txt
nonebot_plugin_mcnews-0.2.2.dist-info/licenses/LICENSE
nonebot_plugin_mcnews/__init__.py
nonebot_plugin_mcnews-0.2.2.dist-info/RECORD
