Metadata-Version: 2.1
Name: nonebot-plugin-mcnews
Version: 0.2.2
Summary: NoneBot2 plugin for CheckMCNewsupdate
Author-Email: CN171-1 <CN171_11_@outlook.com>
License: MIT
Project-URL: Homepage, https://github.com/CN171-1/nonebot-plugin-mcnews
Project-URL: Repository, https://github.com/CN171-1/nonebot-plugin-mcnews
Requires-Python: >=3.9
Requires-Dist: nonebot2<3.0.0,>=2.3.0
Requires-Dist: nonebot-adapter-onebot>=2.1.5
Requires-Dist: nonebot-plugin-apscheduler>=0.2.0
Requires-Dist: httpx>=0.24.0
Requires-Dist: nonebot-plugin-localstore>=0.6.0
